{
  "type": "minecraft:block",
  "pools": [
    {
      "rolls": 1,
      "entries": [
        {
          "type": "minecraft:item",
          "name": "practicalbiomes:obsidian_stone"
        }
      ],
      "conditions": [
        {
          "condition": "minecraft:survives_explosion"
        }
      ]
    },
    {
      "rolls": 1,
      "entries": [
        {
          "type": "minecraft:item",
          "name": "practicalbiomes:obsidian_scrap"
        }
      ],
      "conditions": [
        {
          "condition": "minecraft:survives_explosion"
        },
        {
          "condition": "minecraft:random_chance",
          "chance": 0.5
        }
      ]
    }
  ]
}